llm_manager/__init__.py
llm_manager/config.cpython-311-x86_64-linux-gnu.so
llm_manager/config.pyi
llm_manager/cython.cpython-311-x86_64-linux-gnu.so
llm_manager/cython.pyi
llm_manager/message.cpython-311-x86_64-linux-gnu.so
llm_manager/message.pyi
llm_manager/modal.cpython-311-x86_64-linux-gnu.so
llm_manager/modal.pyi
llm_manager/model.cpython-311-x86_64-linux-gnu.so
llm_manager/model.pyi
llm_manager/prompt.cpython-311-x86_64-linux-gnu.so
llm_manager/prompt.pyi
llm_manager/tools.cpython-311-x86_64-linux-gnu.so
llm_manager/tools.pyi
llm_manager-0.4.5.dist-info/METADATA
llm_manager-0.4.5.dist-info/WHEEL
llm_manager-0.4.5.dist-info/top_level.txt
llm_manager-0.4.5.dist-info/RECORD
