Metadata-Version: 2.1
Name: llm-manager
Version: 0.4.5
Summary: Flash-built LLM workflows
Author: Bigollo
Requires-Dist: portalocker
Requires-Dist: cryptography
Requires-Dist: pydantic
Requires-Dist: requests
Requires-Dist: docker
Requires-Dist: fastmcp
